betfairutil/__init__.py
betfairutil-0.2.0.dist-info/LICENSE
betfairutil-0.2.0.dist-info/METADATA
betfairutil-0.2.0.dist-info/WHEEL
betfairutil-0.2.0.dist-info/top_level.txt
betfairutil-0.2.0.dist-info/RECORD
