Metadata-Version: 2.1
Name: betfairutil
Version: 0.2.0
Summary: Utility functions for working with Betfair data
Home-page: https://github.com/mberk/betfairutil
Author: Maurice Berk
Author-email: maurice@mauriceberk.com
License: UNKNOWN
Platform: UNKNOWN
Classifier: Programming Language :: Python :: 3
Classifier: License :: OSI Approved :: MIT License
Classifier: Operating System :: OS Independent
Requires-Python: >=3.5
License-File: LICENSE
Requires-Dist: betfairlightweight
Requires-Dist: pandas
Provides-Extra: files
Requires-Dist: betfairlightweight (>=2.12.0) ; extra == 'files'
Requires-Dist: smart-open ; extra == 'files'
